datadetective/__init__.py
datadetective/_modidx.py
datadetective/_nbdev.py
datadetective/api.py
datadetective/util.py
datadetective/classification/__init__.py
datadetective/classification/estimate_noise.py
datadetective/classification/rank_noise/__init__.py
datadetective/classification/rank_noise/confidence.py
datadetective/classification/rank_noise/residual.py
lapros/__init__.py
lapros/_modidx.py
lapros/_nbdev.py
lapros/alg.py
lapros/api.py
lapros/util.py
lapros/classification/__init__.py
lapros/classification/estimate_noise.py
lapros/classification/rank_noise/__init__.py
lapros/classification/rank_noise/confidence.py
lapros/classification/rank_noise/residual.py
datadetective-0.4.0.dist-info/LICENSE
datadetective-0.4.0.dist-info/METADATA
datadetective-0.4.0.dist-info/WHEEL
datadetective-0.4.0.dist-info/top_level.txt
datadetective-0.4.0.dist-info/RECORD
