Metadata-Version: 2.1
Name: datadetective
Version: 0.4.0
Summary: The Data Detective, for better Machine Learning & AI
Home-page: https://github.com/Tre-Xanh/datadetective/tree/master/
Author: Vo Chi Cong
Author-email: ccvo@live.jp
License: Apache Software License 2.0
Keywords: AI,data,noise
Classifier: Development Status :: 3 - Alpha
Classifier: Intended Audience :: Developers
Classifier: Natural Language :: English
Classifier: Programming Language :: Python :: 3.8
Classifier: Programming Language :: Python :: 3.9
Classifier: Programming Language :: Python :: 3.10
Classifier: License :: OSI Approved :: Apache Software License
Requires-Python: >=3.8
License-File: LICENSE
Requires-Dist: pip
Requires-Dist: packaging
Requires-Dist: loguru
Requires-Dist: numpy
Requires-Dist: pandas
Requires-Dist: plum-dispatch
Requires-Dist: scipy
Provides-Extra: dev
Requires-Dist: cleanlab ; extra == 'dev'
Requires-Dist: pyarrow ; extra == 'dev'
Requires-Dist: scikit-learn ; extra == 'dev'
